smmregrid/__init__.py
smmregrid/cdogenerate.py
smmregrid/cdogrid.py
smmregrid/checker.py
smmregrid/dimension.py
smmregrid/gridinspector.py
smmregrid/gridtype.py
smmregrid/log.py
smmregrid/regrid.py
smmregrid/util.py
smmregrid/weights.py
smmregrid-0.1.3.dist-info/licenses/LICENSE
smmregrid-0.1.3.dist-info/METADATA
smmregrid-0.1.3.dist-info/WHEEL
smmregrid-0.1.3.dist-info/top_level.txt
smmregrid-0.1.3.dist-info/RECORD
