Metadata-Version: 2.4
Name: smmregrid
Version: 0.1.3
Summary: Regridding based on sparse matrix multiplication
Author-email: Jost von Hardenberg <jost.hardenberg@polito.it>, Paolo Davini <p.davini@isac.cnr.it>, Scott Wales <scott.wales@unimelb.edu.au>
Project-URL: Homepage, https://github.com/jhardenberg/smmregrid
Project-URL: Bug Tracker, https://github.com/jhardenberg/smmregrid/issues
Project-URL: Repository, https://github.com/jhardenberg/smmregrid
Classifier: Programming Language :: Python :: 3
Classifier: Intended Audience :: Science/Research
Classifier: License :: OSI Approved :: Apache Software License
Classifier: Operating System :: OS Independent
Requires-Python: >=3.8
License-File: LICENSE
Requires-Dist: numpy
Requires-Dist: xarray
Requires-Dist: dask
Requires-Dist: netcdf4
Requires-Dist: cfgrib
Requires-Dist: dask
Requires-Dist: sparse
Requires-Dist: cdo
Requires-Dist: numba
Requires-Dist: cfunits
Provides-Extra: tests
Requires-Dist: coverage; extra == "tests"
Requires-Dist: coveralls; extra == "tests"
Requires-Dist: pytest; extra == "tests"
Provides-Extra: docs
Requires-Dist: sphinx<7.0; extra == "docs"
Requires-Dist: sphinx-rtd-theme; extra == "docs"
Provides-Extra: notebooks
Requires-Dist: ipykernel; extra == "notebooks"
Requires-Dist: matplotlib; extra == "notebooks"
Requires-Dist: jinja2; extra == "notebooks"
Provides-Extra: all
Requires-Dist: smmregrid[docs,notebooks,tests]; extra == "all"
Dynamic: license-file
